{
  "lastUpdated": "2025-06-26T07:21:02.246Z",
  "totalGames": 190,
  "games": [
    {
      "date": "2025-07-01T18:30:00.000Z",
      "dateText": "Tue, Jul 1",
      "time": "6:30 PM",
      "homeTeam": "Innisfil Cardinals 10U A",
      "homeTeamCode": "510873",
      "awayTeam": "Barrie Baycats 10U A",
      "awayTeamCode": "510870",
      "location": "Nantyr Park",
      "isCompleted": true,
      "score": {
        "home": 10,
        "away": 8,
        "scoreText": "8-10"
      },
      "division": "10U",
      "tier": "rep-tier-2"
    },
    {
      "date": "2025-07-01T18:30:00.000Z",
      "dateText": "Tue, Jul 1",
      "time": "6:30 PM",
      "homeTeam": "Innisfil Cardinals 10U A",
      "homeTeamCode": "510873",
      "awayTeam": "Barrie Baycats 10U A",
      "awayTeamCode": "510870",
      "location": "Nantyr Park",
      "isCompleted": true,
      "score": {
        "home": 10,
        "away": 8,
        "scoreText": "8-10"
      },
      "division": "10U",
      "tier": "rep-tier-3"
    },
    {
      "date": "2025-06-25T20:30:00.000Z",
      "dateText": "Wed, Jun 25",
      "time": "8:30 PM",
      "homeTeam": "Stouffville Yankees 14U A",
      "homeTeamCode": "510966",
      "awayTeam": "Vaughan Vikings 14U A",
      "awayTeamCode": "518957",
      "location": "Bethesda Sports Field #2",
      "isCompleted": false,
      "score": null,
      "division": "14U",
      "tier": "rep-tier-3"
    },
    {
      "date": "2025-06-25T20:30:00.000Z",
      "dateText": "Wed, Jun 25",
      "time": "8:30 PM",
      "homeTeam": "Vaughan Vikings 15U A",
      "homeTeamCode": "518959",
      "awayTeam": "Georgina Bulldogs 15U B",
      "awayTeamCode": "510998",
      "location": "ROC #1",
      "isCompleted": false,
      "score": null,
      "division": "15U",
      "tier": "rep-tier-2"
    },
    {
      "date": "2025-06-25T20:30:00.000Z",
      "dateText": "Wed, Jun 25",
      "time": "8:30 PM",
      "homeTeam": "Vaughan Vikings 15U A",
      "homeTeamCode": "518959",
      "awayTeam": "Georgina Bulldogs 15U B",
      "awayTeamCode": "510998",
      "location": "ROC #1",
      "isCompleted": false,
      "score": null,
      "division": "15U",
      "tier": "rep-tier-3"
    },
    {
      "date": "2025-06-25T20:30:00.000Z",
      "dateText": "Wed, Jun 25",
      "time": "8:30 PM",
      "homeTeam": "Caledon Nationals 18U A",
      "homeTeamCode": "511026",
      "awayTeam": "Vaughan Vikings 18U AA",
      "awayTeamCode": "518962",
      "location": "Bolton North Hill D1",
      "isCompleted": true,
      "score": {
        "home": 7,
        "away": 6,
        "scoreText": "6-7"
      },
      "division": "18U",
      "tier": "rep-no-tier"
    },
    {
      "date": "2025-06-25T20:00:00.000Z",
      "dateText": "Wed, Jun 25",
      "time": "8:00 PM",
      "homeTeam": "Orangeville Bengals 13U A",
      "homeTeamCode": "510943",
      "awayTeam": "Vaughan Vikings 13U A",
      "awayTeamCode": "518954",
      "location": "ROTORY PARK SOUTH",
      "isCompleted": false,
      "score": null,
      "division": "13U",
      "tier": "rep-tier-2"
    },
    {
      "date": "2025-06-25T20:00:00.000Z",
      "dateText": "Wed, Jun 25",
      "time": "8:00 PM",
      "homeTeam": "Orangeville Bengals 13U A",
      "homeTeamCode": "510943",
      "awayTeam": "Vaughan Vikings 13U A",
      "awayTeamCode": "518954",
      "location": "ROTORY PARK SOUTH",
      "isCompleted": false,
      "score": null,
      "division": "13U",
      "tier": "rep-tier-3"
    },
    {
      "date": "2025-06-25T20:00:00.000Z",
      "dateText": "Wed, Jun 25",
      "time": "8:00 PM",
      "homeTeam": "TNT Thunder 15U DS",
      "homeTeamCode": "511104",
      "awayTeam": "Collingwood Jays 15U DS",
      "awayTeamCode": "511100",
      "location": "Beeton South",
      "isCompleted": false,
      "score": null,
      "division": "15U",
      "tier": "select-all-tiers"
    },
    {
      "date": "2025-06-25T19:30:00.000Z",
      "dateText": "Wed, Jun 25",
      "time": "7:30 PM",
      "homeTeam": "Barrie Baycats 14U A",
      "homeTeamCode": "510959",
      "awayTeam": "Aurora-King Jays 14U A",
      "awayTeamCode": "510958",
      "location": "Lennox Park B",
      "isCompleted": false,
      "score": null,
      "division": "14U",
      "tier": "rep-tier-3"
    },
    {
      "date": "2025-06-25T19:30:00.000Z",
      "dateText": "Wed, Jun 25",
      "time": "7:30 PM",
      "homeTeam": "Richmond Hill Phoenix 16U AA",
      "homeTeamCode": "511012",
      "awayTeam": "Thornhill Reds 16U AA",
      "awayTeamCode": "511013",
      "location": "David Hamilton 1",
      "isCompleted": false,
      "score": null,
      "division": "16U",
      "tier": "rep-tier-2"
    },
    {
      "date": "2025-06-25T19:15:00.000Z",
      "dateText": "Wed, Jun 25",
      "time": "7:15 PM",
      "homeTeam": "Barrie Baycats 17U A",
      "homeTeamCode": "511023",
      "awayTeam": "Stayner White Sox 18U C",
      "awayTeamCode": "519242",
      "location": "Barrie Community Sports Complex",
      "isCompleted": true,
      "score": {
        "home": 3,
        "away": 9,
        "scoreText": "9-3"
      },
      "division": "18U",
      "tier": "rep-no-tier"
    },
    {
      "date": "2025-06-25T19:00:00.000Z",
      "dateText": "Wed, Jun 25",
      "time": "7:00 PM",
      "homeTeam": "Richmond Hill Phoenix 11U AA",
      "homeTeamCode": "510910",
      "awayTeam": "Bradford Tigers 11U AA",
      "awayTeamCode": "510907",
      "location": "David Hamilton #2",
      "isCompleted": false,
      "score": null,
      "division": "11U",
      "tier": "rep-tier-2"
    },
    {
      "date": "2025-06-25T19:00:00.000Z",
      "dateText": "Wed, Jun 25",
      "time": "7:00 PM",
      "homeTeam": "Midland Penetang Twins 11U A",
      "homeTeamCode": "510891",
      "awayTeam": "Muskoka Hornets 11U B",
      "awayTeamCode": "516241",
      "location": "Vasey Park",
      "isCompleted": false,
      "score": null,
      "division": "11U",
      "tier": "rep-tier-2"
    },
    {
      "date": "2025-06-25T19:00:00.000Z",
      "dateText": "Wed, Jun 25",
      "time": "7:00 PM",
      "homeTeam": "Richmond Hill Phoenix 11U AA",
      "homeTeamCode": "510910",
      "awayTeam": "Bradford Tigers 11U AA",
      "awayTeamCode": "510907",
      "location": "David Hamilton #2",
      "isCompleted": false,
      "score": null,
      "division": "11U",
      "tier": "rep-tier-3"
    },
    {
      "date": "2025-06-25T19:00:00.000Z",
      "dateText": "Wed, Jun 25",
      "time": "7:00 PM",
      "homeTeam": "Midland Penetang Twins 11U A",
      "homeTeamCode": "510891",
      "awayTeam": "Muskoka Hornets 11U B",
      "awayTeamCode": "516241",
      "location": "Vasey Park",
      "isCompleted": false,
      "score": null,
      "division": "11U",
      "tier": "rep-tier-3"
    },
    {
      "date": "2025-06-25T19:00:00.000Z",
      "dateText": "Wed, Jun 25",
      "time": "7:00 PM",
      "homeTeam": "Markham Mariners 18U A - Team 2",
      "homeTeamCode": "511031",
      "awayTeam": "Innisfil Cardinals 18U A",
      "awayTeamCode": "511028",
      "location": "Milliken #1",
      "isCompleted": true,
      "score": {
        "home": 3,
        "away": 2,
        "scoreText": "2-3"
      },
      "division": "18U",
      "tier": "rep-no-tier"
    },
    {
      "date": "2025-06-25T18:30:00.000Z",
      "dateText": "Wed, Jun 25",
      "time": "6:30 PM",
      "homeTeam": "Newmarket Hawks 9U A",
      "homeTeamCode": "511062",
      "awayTeam": "Vaughan Vikings 9U A",
      "awayTeamCode": "518948",
      "location": "Fairgrounds #2",
      "isCompleted": false,
      "score": null,
      "division": "9U",
      "tier": "rep-tier-3"
    },
    {
      "date": "2025-06-25T18:30:00.000Z",
      "dateText": "Wed, Jun 25",
      "time": "6:30 PM",
      "homeTeam": "Markham Mariners 9U A",
      "homeTeamCode": "511061",
      "awayTeam": "Stouffville Yankees 9U A",
      "awayTeamCode": "511065",
      "location": "Morgan Park",
      "isCompleted": false,
      "score": null,
      "division": "9U",
      "tier": "rep-tier-3"
    },
    {
      "date": "2025-06-25T18:30:00.000Z",
      "dateText": "Wed, Jun 25",
      "time": "6:30 PM",
      "homeTeam": "Markham Mariners 10U AA",
      "homeTeamCode": "510883",
      "awayTeam": "Vaughan Vikings 10U AA",
      "awayTeamCode": "518949",
      "location": "Reesor Park",
      "isCompleted": false,
      "score": null,
      "division": "10U",
      "tier": "rep-tier-2"
    },
    {
      "date": "2025-06-25T18:30:00.000Z",
      "dateText": "Wed, Jun 25",
      "time": "6:30 PM",
      "homeTeam": "Markham Mariners 10U AA",
      "homeTeamCode": "510883",
      "awayTeam": "Vaughan Vikings 10U AA",
      "awayTeamCode": "518949",
      "location": "Reesor Park",
      "isCompleted": false,
      "score": null,
      "division": "10U",
      "tier": "rep-tier-3"
    },
    {
      "date": "2025-06-25T18:30:00.000Z",
      "dateText": "Wed, Jun 25",
      "time": "6:30 PM",
      "homeTeam": "Barrie Baycats 11U A",
      "homeTeamCode": "510892",
      "awayTeam": "New Lowell Knights 11U D",
      "awayTeamCode": "510917",
      "location": "Sports Complex #13",
      "isCompleted": false,
      "score": null,
      "division": "11U",
      "tier": "rep-tier-2"
    },
    {
      "date": "2025-06-25T18:30:00.000Z",
      "dateText": "Wed, Jun 25",
      "time": "6:30 PM",
      "homeTeam": "Barrie Baycats 11U A",
      "homeTeamCode": "510892",
      "awayTeam": "New Lowell Knights 11U D",
      "awayTeamCode": "510917",
      "location": "Sports Complex #13",
      "isCompleted": false,
      "score": null,
      "division": "11U",
      "tier": "rep-tier-3"
    },
    {
      "date": "2025-06-25T18:30:00.000Z",
      "dateText": "Wed, Jun 25",
      "time": "6:30 PM",
      "homeTeam": "Aurora-King Jays 12U AA",
      "homeTeamCode": "510935",
      "awayTeam": "Newmarket Hawks 12U AA",
      "awayTeamCode": "510923",
      "location": "Hallmark Field 2",
      "isCompleted": false,
      "score": null,
      "division": "12U",
      "tier": "rep-tier-2"
    },
    {
      "date": "2025-06-25T18:30:00.000Z",
      "dateText": "Wed, Jun 25",
      "time": "6:30 PM",
      "homeTeam": "Barrie Baycats 12U A",
      "homeTeamCode": "510919",
      "awayTeam": "TNT Thunder 12U A",
      "awayTeamCode": "510927",
      "location": "Barrie Community Sports Complex - Diamond 12",
      "isCompleted": false,
      "score": null,
      "division": "12U",
      "tier": "rep-tier-2"
    },
    {
      "date": "2025-06-25T18:30:00.000Z",
      "dateText": "Wed, Jun 25",
      "time": "6:30 PM",
      "homeTeam": "Orillia Royals 12U A",
      "homeTeamCode": "510925",
      "awayTeam": "Aurora-King Jays 12U A",
      "awayTeamCode": "510918",
      "location": "YEO Diamond",
      "isCompleted": false,
      "score": null,
      "division": "12U",
      "tier": "rep-tier-2"
    },
    {
      "date": "2025-06-25T18:30:00.000Z",
      "dateText": "Wed, Jun 25",
      "time": "6:30 PM",
      "homeTeam": "Aurora-King Jays 12U AA",
      "homeTeamCode": "510935",
      "awayTeam": "Newmarket Hawks 12U AA",
      "awayTeamCode": "510923",
      "location": "Hallmark Field 2",
      "isCompleted": false,
      "score": null,
      "division": "12U",
      "tier": "rep-tier-3"
    },
    {
      "date": "2025-06-25T18:30:00.000Z",
      "dateText": "Wed, Jun 25",
      "time": "6:30 PM",
      "homeTeam": "Barrie Baycats 12U A",
      "homeTeamCode": "510919",
      "awayTeam": "TNT Thunder 12U A",
      "awayTeamCode": "510927",
      "location": "Barrie Community Sports Complex - Diamond 12",
      "isCompleted": false,
      "score": null,
      "division": "12U",
      "tier": "rep-tier-3"
    },
    {
      "date": "2025-06-25T18:30:00.000Z",
      "dateText": "Wed, Jun 25",
      "time": "6:30 PM",
      "homeTeam": "Orillia Royals 12U A",
      "homeTeamCode": "510925",
      "awayTeam": "Aurora-King Jays 12U A",
      "awayTeamCode": "510918",
      "location": "YEO Diamond",
      "isCompleted": false,
      "score": null,
      "division": "12U",
      "tier": "rep-tier-3"
    },
    {
      "date": "2025-06-25T18:30:00.000Z",
      "dateText": "Wed, Jun 25",
      "time": "6:30 PM",
      "homeTeam": "Barrie Baycats 13U AA",
      "homeTeamCode": "510947",
      "awayTeam": "Aurora-King Jays 13U AA",
      "awayTeamCode": "510946",
      "location": "Lampman Lane Park",
      "isCompleted": false,
      "score": null,
      "division": "13U",
      "tier": "rep-tier-2"
    },
    {
      "date": "2025-06-25T18:30:00.000Z",
      "dateText": "Wed, Jun 25",
      "time": "6:30 PM",
      "homeTeam": "Markham Mariners 13U AA",
      "homeTeamCode": "510949",
      "awayTeam": "Caledon Nationals 13U AA",
      "awayTeamCode": "510948",
      "location": "Milliken Mills #2",
      "isCompleted": false,
      "score": null,
      "division": "13U",
      "tier": "rep-tier-2"
    },
    {
      "date": "2025-06-25T18:30:00.000Z",
      "dateText": "Wed, Jun 25",
      "time": "6:30 PM",
      "homeTeam": "Barrie Baycats 13U AA",
      "homeTeamCode": "510947",
      "awayTeam": "Aurora-King Jays 13U AA",
      "awayTeamCode": "510946",
      "location": "Lampman Lane Park",
      "isCompleted": false,
      "score": null,
      "division": "13U",
      "tier": "rep-tier-3"
    },
    {
      "date": "2025-06-25T18:30:00.000Z",
      "dateText": "Wed, Jun 25",
      "time": "6:30 PM",
      "homeTeam": "Markham Mariners 13U AA",
      "homeTeamCode": "510949",
      "awayTeam": "Caledon Nationals 13U AA",
      "awayTeamCode": "510948",
      "location": "Milliken Mills #2",
      "isCompleted": false,
      "score": null,
      "division": "13U",
      "tier": "rep-tier-3"
    },
    {
      "date": "2025-06-25T18:30:00.000Z",
      "dateText": "Wed, Jun 25",
      "time": "6:30 PM",
      "homeTeam": "Collingwood Jays 15U A",
      "homeTeamCode": "510986",
      "awayTeam": "Caledon Nationals 15U A",
      "awayTeamCode": "510983",
      "location": "Legion Park",
      "isCompleted": false,
      "score": null,
      "division": "15U",
      "tier": "rep-tier-2"
    },
    {
      "date": "2025-06-25T18:30:00.000Z",
      "dateText": "Wed, Jun 25",
      "time": "6:30 PM",
      "homeTeam": "Collingwood Jays 15U A",
      "homeTeamCode": "510986",
      "awayTeam": "Caledon Nationals 15U A",
      "awayTeamCode": "510983",
      "location": "Legion Park",
      "isCompleted": false,
      "score": null,
      "division": "15U",
      "tier": "rep-tier-3"
    },
    {
      "date": "2025-06-25T18:15:00.000Z",
      "dateText": "Wed, Jun 25",
      "time": "6:15 PM",
      "homeTeam": "Richmond Hill Phoenix 10U AA",
      "homeTeamCode": "510885",
      "awayTeam": "Barrie Baycats 10U AA",
      "awayTeamCode": "510882",
      "location": "Morgan Boyle Park",
      "isCompleted": false,
      "score": null,
      "division": "10U",
      "tier": "rep-tier-2"
    },
    {
      "date": "2025-06-25T18:15:00.000Z",
      "dateText": "Wed, Jun 25",
      "time": "6:15 PM",
      "homeTeam": "Richmond Hill Phoenix 10U AA",
      "homeTeamCode": "510885",
      "awayTeam": "Barrie Baycats 10U AA",
      "awayTeamCode": "510882",
      "location": "Morgan Boyle Park",
      "isCompleted": false,
      "score": null,
      "division": "10U",
      "tier": "rep-tier-3"
    },
    {
      "date": "2025-06-25T18:15:00.000Z",
      "dateText": "Wed, Jun 25",
      "time": "6:15 PM",
      "homeTeam": "Georgina Bulldogs 11U B",
      "homeTeamCode": "510916",
      "awayTeam": "Caledon Nationals 11U A",
      "awayTeamCode": "510893",
      "location": "ROC 2",
      "isCompleted": false,
      "score": null,
      "division": "11U",
      "tier": "rep-tier-2"
    },
    {
      "date": "2025-06-25T18:15:00.000Z",
      "dateText": "Wed, Jun 25",
      "time": "6:15 PM",
      "homeTeam": "Georgina Bulldogs 11U B",
      "homeTeamCode": "510916",
      "awayTeam": "Caledon Nationals 11U A",
      "awayTeamCode": "510893",
      "location": "ROC 2",
      "isCompleted": false,
      "score": null,
      "division": "11U",
      "tier": "rep-tier-3"
    },
    {
      "date": "2025-06-25T18:00:00.000Z",
      "dateText": "Wed, Jun 25",
      "time": "6:00 PM",
      "homeTeam": "Collingwood Jays 10U A",
      "homeTeamCode": "510872",
      "awayTeam": "Bradford Tigers 10U A",
      "awayTeamCode": "510871",
      "location": "Heritage Park",
      "isCompleted": false,
      "score": null,
      "division": "10U",
      "tier": "rep-tier-2"
    },
    {
      "date": "2025-06-25T18:00:00.000Z",
      "dateText": "Wed, Jun 25",
      "time": "6:00 PM",
      "homeTeam": "Collingwood Jays 10U A",
      "homeTeamCode": "510872",
      "awayTeam": "Bradford Tigers 10U A",
      "awayTeamCode": "510871",
      "location": "Heritage Park",
      "isCompleted": false,
      "score": null,
      "division": "10U",
      "tier": "rep-tier-3"
    },
    {
      "date": "2025-06-25T18:00:00.000Z",
      "dateText": "Wed, Jun 25",
      "time": "6:00 PM",
      "homeTeam": "Orangeville Bengals 11U AA",
      "homeTeamCode": "510909",
      "awayTeam": "Barrie Baycats 11U AA",
      "awayTeamCode": "510906",
      "location": "Alton Park",
      "isCompleted": false,
      "score": null,
      "division": "11U",
      "tier": "rep-tier-2"
    },
    {
      "date": "2025-06-25T18:00:00.000Z",
      "dateText": "Wed, Jun 25",
      "time": "6:00 PM",
      "homeTeam": "Orangeville Bengals 11U A",
      "homeTeamCode": "510897",
      "awayTeam": "Innisfil Cardinals 11U A",
      "awayTeamCode": "510894",
      "location": "Barbour Field",
      "isCompleted": false,
      "score": null,
      "division": "11U",
      "tier": "rep-tier-2"
    },
    {
      "date": "2025-06-25T18:00:00.000Z",
      "dateText": "Wed, Jun 25",
      "time": "6:00 PM",
      "homeTeam": "Orangeville Bengals 11U AA",
      "homeTeamCode": "510909",
      "awayTeam": "Barrie Baycats 11U AA",
      "awayTeamCode": "510906",
      "location": "Alton Park",
      "isCompleted": false,
      "score": null,
      "division": "11U",
      "tier": "rep-tier-3"
    },
    {
      "date": "2025-06-25T18:00:00.000Z",
      "dateText": "Wed, Jun 25",
      "time": "6:00 PM",
      "homeTeam": "Orangeville Bengals 11U A",
      "homeTeamCode": "510897",
      "awayTeam": "Innisfil Cardinals 11U A",
      "awayTeamCode": "510894",
      "location": "Barbour Field",
      "isCompleted": false,
      "score": null,
      "division": "11U",
      "tier": "rep-tier-3"
    },
    {
      "date": "2025-06-25T18:00:00.000Z",
      "dateText": "Wed, Jun 25",
      "time": "6:00 PM",
      "homeTeam": "Thornhill Reds 13U DS",
      "homeTeamCode": "511096",
      "awayTeam": "Markham Mariners 13U DS -Team 2",
      "awayTeamCode": "511091",
      "location": "Elson Park",
      "isCompleted": false,
      "score": null,
      "division": "13U",
      "tier": "select-all-tiers"
    },
    {
      "date": "2025-06-25T18:00:00.000Z",
      "dateText": "Wed, Jun 25",
      "time": "6:00 PM",
      "homeTeam": "Innisfil Cardinals 14U A",
      "homeTeamCode": "510963",
      "awayTeam": "Thornhill Reds 14U A",
      "awayTeamCode": "510965",
      "location": "Innisfill Rec Centre- North",
      "isCompleted": false,
      "score": null,
      "division": "14U",
      "tier": "rep-tier-3"
    },
    {
      "date": "2025-06-25T18:00:00.000Z",
      "dateText": "Wed, Jun 25",
      "time": "6:00 PM",
      "homeTeam": "Georgina Bulldogs 15U B",
      "homeTeamCode": "510998",
      "awayTeam": "Vaughan Vikings 15U A",
      "awayTeamCode": "518959",
      "location": "ROC #1",
      "isCompleted": false,
      "score": null,
      "division": "15U",
      "tier": "rep-tier-2"
    },
    {
      "date": "2025-06-25T18:00:00.000Z",
      "dateText": "Wed, Jun 25",
      "time": "6:00 PM",
      "homeTeam": "Newmarket Hawks 15U AA",
      "homeTeamCode": "510991",
      "awayTeam": "Aurora-King Jays 15U AA",
      "awayTeamCode": "510993",
      "location": "Whipper Watson",
      "isCompleted": false,
      "score": null,
      "division": "15U",
      "tier": "rep-tier-2"
    },
    {
      "date": "2025-06-25T18:00:00.000Z",
      "dateText": "Wed, Jun 25",
      "time": "6:00 PM",
      "homeTeam": "Muskoka Hornets 15U AA",
      "homeTeamCode": "516244",
      "awayTeam": "Barrie Baycats 15U AA",
      "awayTeamCode": "510987",
      "location": "Kerr Park",
      "isCompleted": false,
      "score": null,
      "division": "15U",
      "tier": "rep-tier-2"
    }
  ]
}