{
  "lastUpdated": "2025-06-08T14:07:02.903Z",
  "totals": {
    "divisions": 52,
    "teams": 197,
    "games": 5559,
    "completed": 1220,
    "upcoming": 4339
  },
  "recentActivity": [
    {
      "date": "2025-06-08T13:15:00.000Z",
      "dateText": "Sun, Jun 8",
      "time": "1:15 PM",
      "homeTeam": "Vaughan Vikings 10U DS",
      "homeTeamCode": "518967",
      "awayTeam": "Richmond Hill Phoenix 11U DS",
      "awayTeamCode": "511081",
      "location": "Matthew Park",
      "isCompleted": false,
      "score": null
    },
    {
      "date": "2025-06-08T12:30:00.000Z",
      "dateText": "Sun, Jun 8",
      "time": "12:30 PM",
      "homeTeam": "Caledon Nationals 13U HS",
      "homeTeamCode": "511098",
      "awayTeam": "Aurora-King Jays 13U DS",
      "awayTeamCode": "511084",
      "location": "Jays Care (Bolton Camp)",
      "isCompleted": false,
      "score": null
    },
    {
      "date": "2025-06-08T12:30:00.000Z",
      "dateText": "Sun, Jun 8",
      "time": "12:30 PM",
      "homeTeam": "Collingwood Jays 15U DS",
      "homeTeamCode": "511100",
      "awayTeam": "Sudbury",
      "awayTeamCode": "500609",
      "location": "Legion Park",
      "isCompleted": false,
      "score": null
    },
    {
      "date": "2025-06-08T12:15:00.000Z",
      "dateText": "Sun, Jun 8",
      "time": "12:15 PM",
      "homeTeam": "Mansfield Cubs 11U DS",
      "homeTeamCode": "511078",
      "awayTeam": "Markham Mariners 11U DS",
      "awayTeamCode": "511079",
      "location": "Mansfield Park",
      "isCompleted": false,
      "score": null
    },
    {
      "date": "2025-06-08T12:00:00.000Z",
      "dateText": "Sun, Jun 8",
      "time": "12:00 PM",
      "homeTeam": "Collingwood Jays (Grey) 13U DS",
      "homeTeamCode": "511087",
      "awayTeam": "TNT Thunder 13U DS",
      "awayTeamCode": "511097",
      "location": "Central Park #1",
      "isCompleted": false,
      "score": null
    }
  ],
  "upcomingGames": [
    {
      "date": "2025-06-08T15:00:00.000Z",
      "dateText": "Sun, Jun 8",
      "time": "3:00 PM",
      "homeTeam": "Ontario Women's",
      "homeTeamCode": "546378",
      "awayTeam": "Stouffville Yankees 14U A",
      "awayTeamCode": "510966",
      "location": "David Hamilton #1",
      "isCompleted": false,
      "score": null
    },
    {
      "date": "2025-06-08T15:00:00.000Z",
      "dateText": "Sun, Jun 8",
      "time": "3:00 PM",
      "homeTeam": "Ontario Women's",
      "homeTeamCode": "546378",
      "awayTeam": "Stouffville Yankees 14U A",
      "awayTeamCode": "510966",
      "location": "David Hamilton #1",
      "isCompleted": false,
      "score": null
    },
    {
      "date": "2025-06-08T15:00:00.000Z",
      "dateText": "Sun, Jun 8",
      "time": "3:00 PM",
      "homeTeam": "Ontario Women's",
      "homeTeamCode": "546378",
      "awayTeam": "Stouffville Yankees 14U A",
      "awayTeamCode": "510966",
      "location": "David Hamilton #1",
      "isCompleted": false,
      "score": null
    },
    {
      "date": "2025-06-08T15:00:00.000Z",
      "dateText": "Sun, Jun 8",
      "time": "3:00 PM",
      "homeTeam": "Ontario Women's",
      "homeTeamCode": "546378",
      "awayTeam": "Stouffville Yankees 14U A",
      "awayTeamCode": "510966",
      "location": "David Hamilton #1",
      "isCompleted": false,
      "score": null
    },
    {
      "date": "2025-06-08T16:00:00.000Z",
      "dateText": "Sun, Jun 8",
      "time": "4:00 PM",
      "homeTeam": "Newmarket Hawks 13U AA",
      "homeTeamCode": "510950",
      "awayTeam": "Caledon Nationals 13U AA",
      "awayTeamCode": "510948",
      "location": "Armstrong Park #1",
      "isCompleted": false,
      "score": null
    }
  ]
}