{
  "lastUpdated": "2025-06-19T18:25:09.108Z",
  "totals": {
    "divisions": 52,
    "teams": 197,
    "games": 5563,
    "completed": 2042,
    "upcoming": 3521
  },
  "recentActivity": [
    {
      "date": "2025-06-19T18:15:00.000Z",
      "dateText": "Thu, Jun 19",
      "time": "6:15 PM",
      "homeTeam": "Georgina Bulldogs 12U B",
      "homeTeamCode": "510939",
      "awayTeam": "TNT Thunder 12U A",
      "awayTeamCode": "510927",
      "location": "ROC 2",
      "isCompleted": false,
      "score": null
    },
    {
      "date": "2025-06-19T18:15:00.000Z",
      "dateText": "Thu, Jun 19",
      "time": "6:15 PM",
      "homeTeam": "Markham Mariners 12U A",
      "homeTeamCode": "510922",
      "awayTeam": "Orillia Royals 12U A",
      "awayTeamCode": "510925",
      "location": "Milliken Mills Diamond 2",
      "isCompleted": false,
      "score": null
    },
    {
      "date": "2025-06-19T18:15:00.000Z",
      "dateText": "Thu, Jun 19",
      "time": "6:15 PM",
      "homeTeam": "Georgina Bulldogs 12U B",
      "homeTeamCode": "510939",
      "awayTeam": "TNT Thunder 12U A",
      "awayTeamCode": "510927",
      "location": "ROC 2",
      "isCompleted": false,
      "score": null
    },
    {
      "date": "2025-06-19T18:15:00.000Z",
      "dateText": "Thu, Jun 19",
      "time": "6:15 PM",
      "homeTeam": "Markham Mariners 12U A",
      "homeTeamCode": "510922",
      "awayTeam": "Orillia Royals 12U A",
      "awayTeamCode": "510925",
      "location": "Milliken Mills Diamond 2",
      "isCompleted": false,
      "score": null
    },
    {
      "date": "2025-06-19T18:15:00.000Z",
      "dateText": "Thu, Jun 19",
      "time": "6:15 PM",
      "homeTeam": "Georgina Bulldogs 12U B",
      "homeTeamCode": "510939",
      "awayTeam": "TNT Thunder 12U A",
      "awayTeamCode": "510927",
      "location": "ROC 2",
      "isCompleted": false,
      "score": null
    }
  ],
  "upcomingGames": [
    {
      "date": "2025-06-19T18:30:00.000Z",
      "dateText": "Thu, Jun 19",
      "time": "6:30 PM",
      "homeTeam": "Markham Mariners 8U A",
      "homeTeamCode": "511057",
      "awayTeam": "Aurora-King Jays 8U A",
      "awayTeamCode": "511050",
      "location": "Morgan Park",
      "isCompleted": false,
      "score": null
    },
    {
      "date": "2025-06-19T18:30:00.000Z",
      "dateText": "Thu, Jun 19",
      "time": "6:30 PM",
      "homeTeam": "Markham Mariners 8U A",
      "homeTeamCode": "511057",
      "awayTeam": "Aurora-King Jays 8U A",
      "awayTeamCode": "511050",
      "location": "Morgan Park",
      "isCompleted": false,
      "score": null
    },
    {
      "date": "2025-06-19T18:30:00.000Z",
      "dateText": "Thu, Jun 19",
      "time": "6:30 PM",
      "homeTeam": "Markham Mariners 8U A",
      "homeTeamCode": "511057",
      "awayTeam": "Aurora-King Jays 8U A",
      "awayTeamCode": "511050",
      "location": "Morgan Park",
      "isCompleted": false,
      "score": null
    },
    {
      "date": "2025-06-19T18:30:00.000Z",
      "dateText": "Thu, Jun 19",
      "time": "6:30 PM",
      "homeTeam": "Markham Mariners 8U A",
      "homeTeamCode": "511057",
      "awayTeam": "Aurora-King Jays 8U A",
      "awayTeamCode": "511050",
      "location": "Morgan Park",
      "isCompleted": false,
      "score": null
    },
    {
      "date": "2025-06-19T18:30:00.000Z",
      "dateText": "Thu, Jun 19",
      "time": "6:30 PM",
      "homeTeam": "Markham Mariners 10U A",
      "homeTeamCode": "510875",
      "awayTeam": "Georgina Bulldogs 10U B",
      "awayTeamCode": "510889",
      "location": "Carlton Park",
      "isCompleted": false,
      "score": null
    }
  ]
}