{
  "lastUpdated": "2025-07-26T13:53:39.403Z",
  "totals": {
    "divisions": 52,
    "teams": 196,
    "games": 5560,
    "completed": 4349,
    "upcoming": 1211
  },
  "recentActivity": [
    {
      "date": "2025-07-26T13:30:00.000Z",
      "dateText": "Sat, Jul 26",
      "time": "1:30 PM",
      "homeTeam": "Newmarket Hawks 13U DS",
      "homeTeamCode": "511093",
      "awayTeam": "Innisfil Cardinals 13U DS - Team 2",
      "awayTeamCode": "511089",
      "location": "Armstrong Family Park #1",
      "isCompleted": false,
      "score": null
    },
    {
      "date": "2025-07-26T13:00:00.000Z",
      "dateText": "Sat, Jul 26",
      "time": "1:00 PM",
      "homeTeam": "Orangeville Bengals 10U AA",
      "homeTeamCode": "510884",
      "awayTeam": "Aurora-King Jays 10U AA",
      "awayTeamCode": "510881",
      "location": "Orangeville",
      "isCompleted": false,
      "score": null
    },
    {
      "date": "2025-07-26T13:00:00.000Z",
      "dateText": "Sat, Jul 26",
      "time": "1:00 PM",
      "homeTeam": "Orangeville Bengals 10U AA",
      "homeTeamCode": "510884",
      "awayTeam": "Aurora-King Jays 10U AA",
      "awayTeamCode": "510881",
      "location": "Orangeville",
      "isCompleted": false,
      "score": null
    },
    {
      "date": "2025-07-26T13:00:00.000Z",
      "dateText": "Sat, Jul 26",
      "time": "1:00 PM",
      "homeTeam": "Orangeville Bengals 10U AA",
      "homeTeamCode": "510884",
      "awayTeam": "Aurora-King Jays 10U AA",
      "awayTeamCode": "510881",
      "location": "Orangeville",
      "isCompleted": false,
      "score": null
    },
    {
      "date": "2025-07-26T13:00:00.000Z",
      "dateText": "Sat, Jul 26",
      "time": "1:00 PM",
      "homeTeam": "Orangeville Bengals 10U AA",
      "homeTeamCode": "510884",
      "awayTeam": "Aurora-King Jays 10U AA",
      "awayTeamCode": "510881",
      "location": "Orangeville",
      "isCompleted": false,
      "score": null
    }
  ],
  "upcomingGames": [
    {
      "date": "2025-07-26T14:00:00.000Z",
      "dateText": "Sat, Jul 26",
      "time": "2:00 PM",
      "homeTeam": "Thornhill Reds 15U AA",
      "homeTeamCode": "510992",
      "awayTeam": "Mansfield Cubs 15U AA",
      "awayTeamCode": "510990",
      "location": "Mansfield Baseball Diamond",
      "isCompleted": false,
      "score": null
    },
    {
      "date": "2025-07-26T14:00:00.000Z",
      "dateText": "Sat, Jul 26",
      "time": "2:00 PM",
      "homeTeam": "Thornhill Reds 15U AA",
      "homeTeamCode": "510992",
      "awayTeam": "Mansfield Cubs 15U AA",
      "awayTeamCode": "510990",
      "location": "Mansfield Baseball Diamond",
      "isCompleted": false,
      "score": null
    },
    {
      "date": "2025-07-26T14:00:00.000Z",
      "dateText": "Sat, Jul 26",
      "time": "2:00 PM",
      "homeTeam": "Thornhill Reds 15U AA",
      "homeTeamCode": "510992",
      "awayTeam": "Mansfield Cubs 15U AA",
      "awayTeamCode": "510990",
      "location": "Mansfield Baseball Diamond",
      "isCompleted": false,
      "score": null
    },
    {
      "date": "2025-07-26T14:00:00.000Z",
      "dateText": "Sat, Jul 26",
      "time": "2:00 PM",
      "homeTeam": "Thornhill Reds 15U AA",
      "homeTeamCode": "510992",
      "awayTeam": "Mansfield Cubs 15U AA",
      "awayTeamCode": "510990",
      "location": "Mansfield Baseball Diamond",
      "isCompleted": false,
      "score": null
    },
    {
      "date": "2025-07-26T15:00:00.000Z",
      "dateText": "Sat, Jul 26",
      "time": "3:00 PM",
      "homeTeam": "Barrie Baycats 13U DS",
      "homeTeamCode": "511085",
      "awayTeam": "Collingwood Jays (Grey) 13U DS",
      "awayTeamCode": "511087",
      "location": "Lampman Lane Park",
      "isCompleted": false,
      "score": null
    }
  ]
}